MSLXPluginHelper/PluginList.py
MSLXPluginHelper/__init__.py
MSLXPluginHelper/example.py
MSLXPluginHelper-0.0.2.dist-info/.pypirc
MSLXPluginHelper-0.0.2.dist-info/LICENSE
MSLXPluginHelper-0.0.2.dist-info/METADATA
MSLXPluginHelper-0.0.2.dist-info/WHEEL
MSLXPluginHelper-0.0.2.dist-info/top_level.txt
MSLXPluginHelper-0.0.2.dist-info/RECORD
