Metadata-Version: 2.1
Name: MSLXPluginHelper
Version: 0.0.2
Summary: Help you create a plugin for MSLX
Home-page: https://github.com/MojaveHao/MSL-X
Author: MojaveHao
Author-email: 353181381@qq.com
Classifier: Programming Language :: Python :: 3.7
Classifier: License :: OSI Approved :: GNU General Public License v3 (GPLv3)
Classifier: Operating System :: OS Independent
License-File: LICENSE
